mypackage/__init__.py
mypackage/__version__.py
mypackage/core.py
mypackage_himansc123-0.1.0.dist-info/LICENSE
mypackage_himansc123-0.1.0.dist-info/METADATA
mypackage_himansc123-0.1.0.dist-info/WHEEL
mypackage_himansc123-0.1.0.dist-info/top_level.txt
mypackage_himansc123-0.1.0.dist-info/RECORD
