Metadata-Version: 2.1
Name: mypackage-himansc123
Version: 0.1.0
Summary: converting a properties file into a desired format .
Home-page: https://bitbucket.org/agile168/pj-devops-rose/src/main/properties-convert/
Author: yauhiman
Author-email: candy.yau@6317.io
License: MIT
Classifier: License :: OSI Approved :: MIT License
Classifier: Programming Language :: Python
Classifier: Programming Language :: Python :: 3
Classifier: Programming Language :: Python :: 3.6
Classifier: Programming Language :: Python :: Implementation :: CPython
Classifier: Programming Language :: Python :: Implementation :: PyPy
Requires-Python: >=3.6.0
License-File: LICENSE
Requires-Dist: argparse
Requires-Dist: jproperties
Requires-Dist: fileinput
